{
  "formInfo": {
    "title": "领导人员德的考核考察测评",
    "organization": "国网浙江省电力有限公司舟山供电公司",
    "period": "2024年",
    "formCode": "1",
    "qrCode": false
  },
  "header": {
    "type": "simple",
    "columns": [
      {
        "id": "name",
        "title": "姓名",
        "type": "text",
        "width": "8%",
        "align": "center"
      },
      {
        "id": "issue1",
        "title": "大局意识差",
        "type": "checkbox",
        "width": "7%",
        "align": "center"
      },
      {
        "id": "issue2",
        "title": "不讲原则，做老好人",
        "type": "checkbox",
        "width": "7%",
        "align": "center"
      },
      {
        "id": "issue3",
        "title": "工作责任心不强，执行力差",
        "type": "checkbox",
        "width": "7%",
        "align": "center"
      },
      {
        "id": "issue4",
        "title": "违反中央"八项规定"精神行为",
        "type": "checkbox",
        "width": "7%",
        "align": "center"
      },
      {
        "id": "issue5",
        "title": "存在阅官习气、衙门作风等问题",
        "type": "checkbox",
        "width": "7%",
        "align": "center"
      },
      {
        "id": "issue6",
        "title": "对个人名利计较较多",
        "type": "checkbox",
        "width": "7%",
        "align": "center"
      },
      {
        "id": "issue7",
        "title": "以不正当手段获取荣誉、学位等利益",
        "type": "checkbox",
        "width": "7%",
        "align": "center"
      },
      {
        "id": "issue8",
        "title": "发表、撰写、散布、散播不当言论的小道消息",
        "type": "checkbox",
        "width": "7%",
        "align": "center"
      },
      {
        "id": "issue9",
        "title": "有夫妻关系不和睦、不孝顺长辈的现象",
        "type": "checkbox",
        "width": "7%",
        "align": "center"
      },
      {
        "id": "issue10",
        "title": "作风不检点、不注重自身形象",
        "type": "checkbox",
        "width": "7%",
        "align": "center"
      },
      {
        "id": "issue11",
        "title": "拉帮结派，存在山头主义",
        "type": "checkbox",
        "width": "7%",
        "align": "center"
      },
      {
        "id": "issue12",
        "title": "消费与正常收入存在较大反差",
        "type": "checkbox",
        "width": "7%",
        "align": "center"
      },
      {
        "id": "issue13",
        "title": "对亲属和身边工作人员要求不严，为其谋求不正当利益",
        "type": "checkbox",
        "width": "7%",
        "align": "center"
      }
    ]
  },
  "body": {
    "type": "fixed",
    "rows": [
      {
        "id": "row1",
        "type": "data",
        "cells": [
          {
            "columnId": "name",
            "value": "汪宇怀",
            "type": "text",
            "readonly": true
          },
          {
            "columnId": "issue1",
            "value": "",
            "type": "checkbox",
            "readonly": false
          },
          {
            "columnId": "issue2",
            "value": "",
            "type": "checkbox",
            "readonly": false
          },
          {
            "columnId": "issue3",
            "value": "",
            "type": "checkbox",
            "readonly": false
          },
          {
            "columnId": "issue4",
            "value": "",
            "type": "checkbox",
            "readonly": false
          },
          {
            "columnId": "issue5",
            "value": "",
            "type": "checkbox",
            "readonly": false
          },
          {
            "columnId": "issue6",
            "value": "",
            "type": "checkbox",
            "readonly": false
          },
          {
            "columnId": "issue7",
            "value": "",
            "type": "checkbox",
            "readonly": false
          },
          {
            "columnId": "issue8",
            "value": "",
            "type": "checkbox",
            "readonly": false
          },
          {
            "columnId": "issue9",
            "value": "",
            "type": "checkbox",
            "readonly": false
          },
          {
            "columnId": "issue10",
            "value": "",
            "type": "checkbox",
            "readonly": false
          },
          {
            "columnId": "issue11",
            "value": "",
            "type": "checkbox",
            "readonly": false
          },
          {
            "columnId": "issue12",
            "value": "",
            "type": "checkbox",
            "readonly": false
          },
          {
            "columnId": "issue13",
            "value": "",
            "type": "checkbox",
            "readonly": false
          }
        ]
      },
      {
        "id": "row2",
        "type": "data",
        "cells": [
          {
            "columnId": "name",
            "value": "虞昉",
            "type": "text",
            "readonly": true
          },
          {
            "columnId": "issue1",
            "value": "",
            "type": "checkbox",
            "readonly": false
          },
          {
            "columnId": "issue2",
            "value": "",
            "type": "checkbox",
            "readonly": false
          },
          {
            "columnId": "issue3",
            "value": "",
            "type": "checkbox",
            "readonly": false
          },
          {
            "columnId": "issue4",
            "value": "",
            "type": "checkbox",
            "readonly": false
          },
          {
            "columnId": "issue5",
            "value": "",
            "type": "checkbox",
            "readonly": false
          },
          {
            "columnId": "issue6",
            "value": "",
            "type": "checkbox",
            "readonly": false
          },
          {
            "columnId": "issue7",
            "value": "",
            "type": "checkbox",
            "readonly": false
          },
          {
            "columnId": "issue8",
            "value": "",
            "type": "checkbox",
            "readonly": false
          },
          {
            "columnId": "issue9",
            "value": "",
            "type": "checkbox",
            "readonly": false
          },
          {
            "columnId": "issue10",
            "value": "",
            "type": "checkbox",
            "readonly": false
          },
          {
            "columnId": "issue11",
            "value": "",
            "type": "checkbox",
            "readonly": false
          },
          {
            "columnId": "issue12",
            "value": "",
            "type": "checkbox",
            "readonly": false
          },
          {
            "columnId": "issue13",
            "value": "",
            "type": "checkbox",
            "readonly": false
          }
        ]
      },
      {
        "id": "row3",
        "type": "data",
        "cells": [
          {
            "columnId": "name",
            "value": "周波达",
            "type": "text",
            "readonly": true
          },
          {
            "columnId": "issue1",
            "value": "",
            "type": "checkbox",
            "readonly": false
          },
          {
            "columnId": "issue2",
            "value": "",
            "type": "checkbox",
            "readonly": false
          },
          {
            "columnId": "issue3",
            "value": "",
            "type": "checkbox",
            "readonly": false
          },
          {
            "columnId": "issue4",
            "value": "",
            "type": "checkbox",
            "readonly": false
          },
          {
            "columnId": "issue5",
            "value": "",
            "type": "checkbox",
            "readonly": false
          },
          {
            "columnId": "issue6",
            "value": "",
            "type": "checkbox",
            "readonly": false
          },
          {
            "columnId": "issue7",
            "value": "",
            "type": "checkbox",
            "readonly": false
          },
          {
            "columnId": "issue8",
            "value": "",
            "type": "checkbox",
            "readonly": false
          },
          {
            "columnId": "issue9",
            "value": "",
            "type": "checkbox",
            "readonly": false
          },
          {
            "columnId": "issue10",
            "value": "",
            "type": "checkbox",
            "readonly": false
          },
          {
            "columnId": "issue11",
            "value": "",
            "type": "checkbox",
            "readonly": false
          },
          {
            "columnId": "issue12",
            "value": "",
            "type": "checkbox",
            "readonly": false
          },
          {
            "columnId": "issue13",
            "value": "",
            "type": "checkbox",
            "readonly": false
          }
        ]
      },
      {
        "id": "row4",
        "type": "data",
        "cells": [
          {
            "columnId": "name",
            "value": "张平",
            "type": "text",
            "readonly": true
          },
          {
            "columnId": "issue1",
            "value": "",
            "type": "checkbox",
            "readonly": false
          },
          {
            "columnId": "issue2",
            "value": "",
            "type": "checkbox",
            "readonly": false
          },
          {
            "columnId": "issue3",
            "value": "",
            "type": "checkbox",
            "readonly": false
          },
          {
            "columnId": "issue4",
            "value": "",
            "type": "checkbox",
            "readonly": false
          },
          {
            "columnId": "issue5",
            "value": "",
            "type": "checkbox",
            "readonly": false
          },
          {
            "columnId": "issue6",
            "value": "",
            "type": "checkbox",
            "readonly": false
          },
          {
            "columnId": "issue7",
            "value": "",
            "type": "checkbox",
            "readonly": false
          },
          {
            "columnId": "issue8",
            "value": "",
            "type": "checkbox",
            "readonly": false
          },
          {
            "columnId": "issue9",
            "value": "",
            "type": "checkbox",
            "readonly": false
          },
          {
            "columnId": "issue10",
            "value": "",
            "type": "checkbox",
            "readonly": false
          },
          {
            "columnId": "issue11",
            "value": "",
            "type": "checkbox",
            "readonly": false
          },
          {
            "columnId": "issue12",
            "value": "",
            "type": "checkbox",
            "readonly": false
          },
          {
            "columnId": "issue13",
            "value": "",
            "type": "checkbox",
            "readonly": false
          }
        ]
      },
      {
        "id": "row5",
        "type": "data",
        "cells": [
          {
            "columnId": "name",
            "value": "王广",
            "type": "text",
            "readonly": true
          },
          {
            "columnId": "issue1",
            "value": "",
            "type": "checkbox",
            "readonly": false
          },
          {
            "columnId": "issue2",
            "value": "",
            "type": "checkbox",
            "readonly": false
          },
          {
            "columnId": "issue3",
            "value": "",
            "type": "checkbox",
            "readonly": false
          },
          {
            "columnId": "issue4",
            "value": "",
            "type": "checkbox",
            "readonly": false
          },
          {
            "columnId": "issue5",
            "value": "",
            "type": "checkbox",
            "readonly": false
          },
          {
            "columnId": "issue6",
            "value": "",
            "type": "checkbox",
            "readonly": false
          },
          {
            "columnId": "issue7",
            "value": "",
            "type": "checkbox",
            "readonly": false
          },
          {
            "columnId": "issue8",
            "value": "",
            "type": "checkbox",
            "readonly": false
          },
          {
            "columnId": "issue9",
            "value": "",
            "type": "checkbox",
            "readonly": false
          },
          {
            "columnId": "issue10",
            "value": "",
            "type": "checkbox",
            "readonly": false
          },
          {
            "columnId": "issue11",
            "value": "",
            "type": "checkbox",
            "readonly": false
          },
          {
            "columnId": "issue12",
            "value": "",
            "type": "checkbox",
            "readonly": false
          },
          {
            "columnId": "issue13",
            "value": "",
            "type": "checkbox",
            "readonly": false
          }
        ]
      },
      {
        "id": "row6",
        "type": "data",
        "cells": [
          {
            "columnId": "name",
            "value": "梁帅伟",
            "type": "text",
            "readonly": true
          },
          {
            "columnId": "issue1",
            "value": "",
            "type": "checkbox",
            "readonly": false
          },
          {
            "columnId": "issue2",
            "value": "",
            "type": "checkbox",
            "readonly": false
          },
          {
            "columnId": "issue3",
            "value": "",
            "type": "checkbox",
            "readonly": false
          },
          {
            "columnId": "issue4",
            "value": "",
            "type": "checkbox",
            "readonly": false
          },
          {
            "columnId": "issue5",
            "value": "",
            "type": "checkbox",
            "readonly": false
          },
          {
            "columnId": "issue6",
            "value": "",
            "type": "checkbox",
            "readonly": false
          },
          {
            "columnId": "issue7",
            "value": "",
            "type": "checkbox",
            "readonly": false
          },
          {
            "columnId": "issue8",
            "value": "",
            "type": "checkbox",
            "readonly": false
          },
          {
            "columnId": "issue9",
            "value": "",
            "type": "checkbox",
            "readonly": false
          },
          {
            "columnId": "issue10",
            "value": "",
            "type": "checkbox",
            "readonly": false
          },
          {
            "columnId": "issue11",
            "value": "",
            "type": "checkbox",
            "readonly": false
          },
          {
            "columnId": "issue12",
            "value": "",
            "type": "checkbox",
            "readonly": false
          },
          {
            "columnId": "issue13",
            "value": "",
            "type": "checkbox",
            "readonly": false
          }
        ]
      },
      {
        "id": "row7",
        "type": "data",
        "cells": [
          {
            "columnId": "name",
            "value": "山托",
            "type": "text",
            "readonly": true
          },
          {
            "columnId": "issue1",
            "value": "",
            "type": "checkbox",
            "readonly": false
          },
          {
            "columnId": "issue2",
            "value": "",
            "type": "checkbox",
            "readonly": false
          },
          {
            "columnId": "issue3",
            "value": "",
            "type": "checkbox",
            "readonly": false
          },
          {
            "columnId": "issue4",
            "value": "",
            "type": "checkbox",
            "readonly": false
          },
          {
            "columnId": "issue5",
            "value": "",
            "type": "checkbox",
            "readonly": false
          },
          {
            "columnId": "issue6",
            "value": "",
            "type": "checkbox",
            "readonly": false
          },
          {
            "columnId": "issue7",
            "value": "",
            "type": "checkbox",
            "readonly": false
          },
          {
            "columnId": "issue8",
            "value": "",
            "type": "checkbox",
            "readonly": false
          },
          {
            "columnId": "issue9",
            "value": "",
            "type": "checkbox",
            "readonly": false
          },
          {
            "columnId": "issue10",
            "value": "",
            "type": "checkbox",
            "readonly": false
          },
          {
            "columnId": "issue11",
            "value": "",
            "type": "checkbox",
            "readonly": false
          },
          {
            "columnId": "issue12",
            "value": "",
            "type": "checkbox",
            "readonly": false
          },
          {
            "columnId": "issue13",
            "value": "",
            "type": "checkbox",
            "readonly": false
          }
        ]
      },
      {
        "id": "row8",
        "type": "data",
        "cells": [
          {
            "columnId": "name",
            "value": "胡俊华",
            "type": "text",
            "readonly": true
          },
          {
            "columnId": "issue1",
            "value": "",
            "type": "checkbox",
            "readonly": false
          },
          {
            "columnId": "issue2",
            "value": "",
            "type": "checkbox",
            "readonly": false
          },
          {
            "columnId": "issue3",
            "value": "",
            "type": "checkbox",
            "readonly": false
          },
          {
            "columnId": "issue4",
            "value": "",
            "type": "checkbox",
            "readonly": false
          },
          {
            "columnId": "issue5",
            "value": "",
            "type": "checkbox",
            "readonly": false
          },
          {
            "columnId": "issue6",
            "value": "",
            "type": "checkbox",
            "readonly": false
          },
          {
            "columnId": "issue7",
            "value": "",
            "type": "checkbox",
            "readonly": false
          },
          {
            "columnId": "issue8",
            "value": "",
            "type": "checkbox",
            "readonly": false
          },
          {
            "columnId": "issue9",
            "value": "",
            "type": "checkbox",
            "readonly": false
          },
          {
            "columnId": "issue10",
            "value": "",
            "type": "checkbox",
            "readonly": false
          },
          {
            "columnId": "issue11",
            "value": "",
            "type": "checkbox",
            "readonly": false
          },
          {
            "columnId": "issue12",
            "value": "",
            "type": "checkbox",
            "readonly": false
          },
          {
            "columnId": "issue13",
            "value": "",
            "type": "checkbox",
            "readonly": false
          }
        ]
      },
      {
        "id": "row9",
        "type": "data",
        "cells": [
          {
            "columnId": "name",
            "value": "石礁",
            "type": "text",
            "readonly": true
          },
          {
            "columnId": "issue1",
            "value": "",
            "type": "checkbox",
            "readonly": false
          },
          {
            "columnId": "issue2",
            "value": "",
            "type": "checkbox",
            "readonly": false
          },
          {
            "columnId": "issue3",
            "value": "",
            "type": "checkbox",
            "readonly": false
          },
          {
            "columnId": "issue4",
            "value": "",
            "type": "checkbox",
            "readonly": false
          },
          {
            "columnId": "issue5",
            "value": "",
            "type": "checkbox",
            "readonly": false
          },
          {
            "columnId": "issue6",
            "value": "",
            "type": "checkbox",
            "readonly": false
          },
          {
            "columnId": "issue7",
            "value": "",
            "type": "checkbox",
            "readonly": false
          },
          {
            "columnId": "issue8",
            "value": "",
            "type": "checkbox",
            "readonly": false
          },
          {
            "columnId": "issue9",
            "value": "",
            "type": "checkbox",
            "readonly": false
          },
          {
            "columnId": "issue10",
            "value": "",
            "type": "checkbox",
            "readonly": false
          },
          {
            "columnId": "issue11",
            "value": "",
            "type": "checkbox",
            "readonly": false
          },
          {
            "columnId": "issue12",
            "value": "",
            "type": "checkbox",
            "readonly": false
          },
          {
            "columnId": "issue13",
            "value": "",
            "type": "checkbox",
            "readonly": false
          }
        ]
      }
    ]
  },
  "footer": {
    "notes": [
      "1、考核对象在德的方面如有以上情况，请在相应栏里画"〇"。",
      "2、针对上述人员的具体事例，请填写在"需要说明的事项"栏。"
    ],
    "additionalFields": [
      {
        "id": "notes",
        "title": "需要说明的事项",
        "type": "textarea",
        "required": false
      }
    ]
  },
  "validation": {
    "rules": []
  }
}
